xia_engine_sql/__init__.py
xia_engine_sql/engine.cpython-39-darwin.so
xia_engine_sql-0.2.11.dist-info/LICENSE.txt
xia_engine_sql-0.2.11.dist-info/METADATA
xia_engine_sql-0.2.11.dist-info/WHEEL
xia_engine_sql-0.2.11.dist-info/top_level.txt
xia_engine_sql-0.2.11.dist-info/RECORD
