Metadata-Version: 2.1
Name: xia-engine-sql
Version: 0.2.11
Home-page: https://develop.x-i-a.com/docs/xia-engine-sql/0.2.11/index.html
Author: X-I-A
Author-email: admin@x-i-a.com
Requires-Python: >=3.9
License-File: LICENSE.txt
Requires-Dist: xia-engine
